titanic_model/VERSION
titanic_model/__init__.py
titanic_model/config.yml
titanic_model/pipeline.py
titanic_model/predict.py
titanic_model/train_pipeline.py
titanic_model/config/__init__.py
titanic_model/config/core.py
titanic_model/datasets/__init__.py
titanic_model/processing/__init__.py
titanic_model/processing/data_manager.py
titanic_model/processing/features.py
titanic_model/processing/validation.py
titanic_model/trained_models/__init__.py
titanic_model/trained_models/titanic_pipeline_output_v1.0.3.pkl
charbel_titanic_classification_model-1.0.3.dist-info/METADATA
charbel_titanic_classification_model-1.0.3.dist-info/WHEEL
charbel_titanic_classification_model-1.0.3.dist-info/top_level.txt
charbel_titanic_classification_model-1.0.3.dist-info/RECORD
